leon_test_package
