Metadata-Version: 1.0
Name: leon-test-package
Version: 0.2
Summary: The funniest joke in the world
Home-page: http://github.com/yangli0534/leon_test_package
Author: yangli0534
Author-email: yangli0534@yahoo.com
License: MIT
Platform: UNKNOWN
